py_trezor_crypto_ph4-0.1.1.dist-info/METADATA
py_trezor_crypto_ph4-0.1.1.dist-info/RECORD
py_trezor_crypto_ph4-0.1.1.dist-info/WHEEL
py_trezor_crypto_ph4-0.1.1.dist-info/top_level.txt
trezor_crypto/__init__.py
trezor_crypto/cffi_build.py
trezor_crypto/mod_base.py
trezor_crypto/stub_cffi.py
trezor_crypto/stub_ctype.py
trezor_crypto/tcry_cffi.abi3.so
trezor_crypto/tcry_ctype.cpython-36m-darwin.so
trezor_crypto/trezor_cfunc.py
trezor_crypto/trezor_cfunc_gen.py
trezor_crypto/trezor_ctypes.py
trezor_crypto/trezor_ctypes_gen.py
trezor_crypto_tests/__init__.py
trezor_crypto_tests/test.py
trezor_crypto_tests/test.pyc
