Metadata-Version: 2.1
Name: py-trezor-crypto-ph4
Version: 0.1.1
Summary: Trezor-crypto python binding
Home-page: https://github.com/ph4r05/py-trezor-crypto
Author: Dusan Klinec
Author-email: dusan.klinec@gmail.com
License: MIT
Platform: UNKNOWN
Classifier: Development Status :: 3 - Alpha
Classifier: Intended Audience :: Developers
Classifier: Programming Language :: Python
Classifier: Programming Language :: Python :: 3.5
Classifier: Programming Language :: Python :: 3.6
Classifier: Topic :: Security
Provides-Extra: docs
Provides-Extra: dev
Requires-Dist: cffi (>=1.1)
Requires-Dist: shlib
Requires-Dist: ctypeslib2
Requires-Dist: pycparser
Provides-Extra: dev
Requires-Dist: nose; extra == 'dev'
Requires-Dist: pep8; extra == 'dev'
Requires-Dist: tox; extra == 'dev'
Requires-Dist: aiounittest; extra == 'dev'
Requires-Dist: requests; extra == 'dev'
Requires-Dist: pympler; extra == 'dev'
Requires-Dist: pypandoc; extra == 'dev'
Requires-Dist: pandoc; extra == 'dev'
Requires-Dist: pycparser; extra == 'dev'
Requires-Dist: ctypeslib2; extra == 'dev'
Requires-Dist: shlib; extra == 'dev'
Provides-Extra: docs
Requires-Dist: Sphinx (>=1.0); extra == 'docs'
Requires-Dist: sphinx-rtd-theme; extra == 'docs'
Requires-Dist: sphinxcontrib-programoutput; extra == 'docs'
